shirkhan/__init__.py
shirkhan/shir_archive.py
shirkhan/shir_csv.py
shirkhan/shir_email.py
shirkhan/shir_encode_decode.py
shirkhan/shir_encryption.py
shirkhan/shir_file.py
shirkhan/shir_metadata.py
shirkhan/shir_mp3.py
shirkhan/shir_shirkhan_alphabet.py
shirkhan/shir_string.py
shirkhan/shir_syllable.py
shirkhan/shir_textgrid.py
shirkhan/shir_wav.py
shirkhan/shir_excel/__init__.py
shirkhan/shir_excel/xls.py
shirkhan/shir_excel/xlsx.py
shirkhan-0.0.28.dist-info/LICENSE
shirkhan-0.0.28.dist-info/METADATA
shirkhan-0.0.28.dist-info/WHEEL
shirkhan-0.0.28.dist-info/top_level.txt
shirkhan-0.0.28.dist-info/RECORD
