Metadata-Version: 2.1
Name: shirkhan
Version: 0.0.28
Summary: shirkhan tools
Home-page: https://github.com/ishirkhan
Author: shirkhan
Author-email: uybabbage@hotmail.com
License: UNKNOWN
Platform: UNKNOWN
Classifier: Programming Language :: Python :: 3.9
Classifier: License :: OSI Approved :: MIT License
Classifier: Operating System :: OS Independent
License-File: LICENSE
Requires-Dist: pycryptodome (==3.10.1)
Requires-Dist: xlrd (==2.0.1)
Requires-Dist: openpyxl (==3.0.7)
Requires-Dist: praatio (==4.2.1)
Provides-Extra: shirkhan_extra
Requires-Dist: pydub (==0.25.1) ; extra == 'shirkhan_extra'
